AUTHORS.md
LICENSE.txt
README.md
setup.cfg
setup.py
src/akkd_file_tree.egg-info/PKG-INFO
src/akkd_file_tree.egg-info/SOURCES.txt
src/akkd_file_tree.egg-info/dependency_links.txt
src/akkd_file_tree.egg-info/entry_points.txt
src/akkd_file_tree.egg-info/not-zip-safe
src/akkd_file_tree.egg-info/requires.txt
src/akkd_file_tree.egg-info/top_level.txt
src/file_tree/__init__.py
src/file_tree/_file_tree.py
src/file_tree/version.py